Workbook

Sheet Tables
A1: TableNames | B1: SheetNames | C1: VirtualNames
A2: GeneralInformation | B2: GeneralInformation | C2: GeneralInformation
A3: Items | B3: Items | C3: Items
A4: ChargesAndDeductions | B4: ChargesAndDeductions | C4: ChargesAndDeductions
A5: OtherCharges | B5: OtherCharges | C5: OtherCharges
A6: SerialNos | B6: SerialNos | C6: SerialNos
A7: CGST | B7: CGST | C7: CGST
A8: SGST | B8: SGST | C8: SGST
A9: IGST | B9: IGST | C9: IGST
A10: CESS | B10: CESS | C10: CESS
A11: TCS | B11: TCS | C11: TCS
A12: BillsReceivable | B12: BillsReceivable | C12: BillsReceivable
... A25: Allocations | B25: Allocations | C25: Allocations

Sheet GeneralInformation
A1: VoucherType | B1: Date | C1: Branch | D1: Location | E1: TransactionCurrency | F1: RegistrationType | G1: ExchangeRate | H1: CurrencyCheck | I1: SalesInvoiceNo | J1: SalesInvoiceDate | K1: PartyAccountCode | L1: PartyAccount | M1: PartyDescription | N1: PlaceOfSupply | O1: GSTTransactionType | P1: MobileNo | Q1: CreditPeriod | R1: DueDate | S1: SalesReturnsAccountCode | T1: SalesReturnsAccount | U1: ApplyTCS | V1: TCSTransactionNature | W1: BatchPolicy | X1: PriceList | Y1: VoucherDiscountPercentage | Z1: Executive | AA1: ShippingAddressisDifferentfromBillingAddress | AB1: ShippingAddress | AC1: Remarks
A2: AT_SRT | B2: 45849 | C2: AT_Branch 1_Reg | D2: AT_Branch 1_Location 1 | E2: INR | F2: 1 | G2: 1 | H2: 0 | I2: SI1 1 | J2: 45849 | K2: At_Cus_Reg_Intra | L2: At_Cus_Reg_Intra | M2: Customer Reg Intra | N2: Intra State | O2: Intra State Sales Returns from Registered Dealers | Q2: 91 | R2: 45940 | S2: AT_Sales Return Acc 1 | T2: AT_Sales Return Acc 1 | U2: 1 | V2: AT_TCS Transaction Nature 1 | W2: AT-Purchase Batch Policy_CIDNE | X2: AT_Exclusive Sales Price List 1 | Y2: 1.11 | Z2: AT_Executive 2 | AA2: 0 | AC2: PVREM1

Sheet Items
A1: ProductCode | B1: MasterType | C1: Product | D1: Description | E1: HSNCode | F1: GoodsOrServices | G1: IsBatch | H1: IsSerialNo | I1: BatchDetails | J1: ProductBatch | K1: History | L1: SalesReturnsAccount | M1: SKU | N1: UOM | O1: ConversionFactor | P1: StorageBin | Q1: SerialNos | R1: Quantity | S1: QuantityInSKU | T1: FreeQuantity | U1: FreeQuantityInSKU | V1: NoOfPacks | W1: MRP | X1: MRPAmount | Y1: UnitRate | Z1: GrossAmount | AA1: VoucherDiscountPercentage | AB1: VoucherDiscount | AC1: PartyDiscountPercentage | AD1: PartyDiscount | AE1: DiscountBasis1 | AF1: Discount1 | AG1: DiscountAmount1 | AH1: DiscountBasis2 | AI1: Discount2 | AJ1: DiscountAmount2 | AK1: DiscountBasis3 | AL1: Discount3 | AM1: DiscountAmount3 | AN1: InclusiveTax | AO1: HSN | AP1: GSTProductCategory | AQ1: CESSProductCategory | AR1: GSTAssessableValue | AS1: GSTPercentage | AT1: CGST | AU1: SGST | AV1: IGST | AW1: CESS | AX1: GSTAmount | AY1: NetAmount | AZ1: NetAmountInCompanyCurrency | BA1: Department | BB1: Project | BC1: ProfitCentre | BD1: CostCentre | BE1: Comments | BF1: Info1 | BG1: Info2 | BH1: Info3 | BI1: Info4 | BJ1: Info5 | BK1: Value1 | BL1: Value2 | BM1: Value3 | BN1: Value4 | BO1: Value5 | BP1: Date1 | BQ1: Date2 | BR1: Date3 | BS1: Bool1 | BT1: Bool2 | BU1: Bool3
A2: AT_Product 1 | B2: Products | C2: AT_Product 1 | D2: P1 | E2: 8967 | F2: G | G2: 0 | H2: 0 | I2: 1 | J2: AT_Product 1 | K2: 0 | L2: AT_Sales Return Acc 1 | M2: Nos | N2: Nos | O2: 1 | P2: AT_Branch 1_Location 1 Default Bin | Q2: 0 | R2: 1.123 | S2: 1.123 | T2: 1.012 | U2: 1.012 | V2: 1 | W2: 500.11 | X2: 561.62 | Y2: 250.11 | Z2: 280.87 | AA2: 1.11 | AB2: 3.12 | AC2: 1.12 | AD2: 3.15 | AE2: % on Gross | AF2: 1.02 | AG2: 2.86 | AH2: % on Gross | AI2: 1.07 | AJ2: 3.01 | AK2: % on Gross | AL2: 1.23 | AM2: 3.45 | AN2: 0 | AO2: AT_HSN Code 1 | AP2: GST 12% | AQ2: CESS 1% | AR2: 265.28 | AS2: 12 | AT2: 15.92 | AU2: 15.92 | AV2: 0 | AW2: 2.65 | AX2: 34.49 | AY2: 299.77 | AZ2: 299.77 | BA2: Department 1 | BB2: Project 1 | BC2: Profit Centre 1 | BD2: Cost Centre 1 | BE2: PVICMNT1 | BF2: INF1 | BG2: INF6 | BH2: INF11 | BI2: INF16 | BJ2: INF22 | BK2: 1.28 | BL2: 1.34 | BM2: 1.39 | BN2: 1.45 | BO2: 1.51 | BP2: 45850 | BQ2: 45855 | BR2: 45856 | BS2: 1 | BT2: 1 | BU2: 1
A3: AT_Product 2 | B3: Products | C3: AT_Product 2 | D3: P2 | E3: 8967 | F3: G | G3: 0 | H3: 0 | I3: 1 | J3: AT_Product 2 | K3: 0 | L3: AT_Sales Return Acc 2 | M3: Nos | N3: Nos | O3: 1 | P3: AT_Branch 1_Location 1 Default Bin | Q3: 0 | R3: 1.124 | S3: 1.124 | T3: 1.103 | U3: 1.103 | V3: 2 | W3: 500.12 | X3: 562.13 | Y3: 250.12 | Z3: 281.13 | AA3: 1.11 | AB3: 3.12 | AC3: 1.13 | AD3: 3.18 | AE3: % on Gross | AF3: 1.03 | AG3: 2.9 | AH3: % on Gross-Disc1 | AI3: 1.08 | AJ3: 3 | AK3: % on Gross-Disc1 | AL3: 1.24 | AM3: 3.45 | AN3: 0 | AO3: AT_HSN Code 1 | AP3: GST 12% | AQ3: CESS 1% | AR3: 265.48 | AS3: 12 | AT3: 15.93 | AU3: 15.93 | AV3: 0 | AW3: 2.65 | AX3: 34.51 | AY3: 299.99 | AZ3: 299.99 | BA3: AT_Department 2 | BB3: AT_Project 2 | BC3: AT_Profit Center 2 | BD3: AT_Cost Center 2 | BE3: PVICMNT2 | BF3: INF2 | BG3: INF7 | BH3: INF12 | BI3: INF17 | BJ3: INF23 | BK3: 1.29 | BL3: 1.35 | BM3: 1.41 | BN3: 1.46 | BO3: 1.52 | BP3: 45851 | BQ3: 45857 | BR3: 45858 | BS3: 1 | BT3: 1 | BU3: 1
A4: AT_Product 5 | B4: Products | C4: AT_Product 5 | E4: 7777 | F4: G | G4: 0 | H4: 0 | I4: 1 | J4: AT_Product 5 | K4: 0 | L4: AT_Sales Return Acc 3 | M4: Nos | N4: Nos | O4: 1 | P4: AT_Branch 1_Location 1 Default Bin | Q4: 0 | R4: 1.126 | S4: 1.126 | T4: 1.105 | U4: 1.105 | V4: 3 | W4: 1000.13 | X4: 1126.15 | Y4: 100.13 | Z4: 112.75 | AA4: 1.11 | AB4: 1.25 | AC4: 1.16 | AD4: 1.31 | AE4: % on Gross - Voucher Disc - Party Disc | AF4: 1.04 | AG4: 1.17 | AH4: % on Gross-Disc1-V Disc-P Disc | AI4: 1.09 | AJ4: 1.22 | AK4: % on Gross-Disc1-V Disc-P Disc | AL4: 1.25 | AM4: 1.39 | AN4: 0 | AO4: AT_HSN Code 2 | AP4: GST 18% | AQ4: CESS 10% | AR4: 106.41 | AS4: 18 | AT4: 9.58 | AU4: 9.58 | AV4: 0 | AW4: 10.64 | AX4: 29.8 | AY4: 136.21 | AZ4: 136.21 | BA4: AT_Department 3 | BB4: AT_Project 3 | BC4: AT_Profit Center 3 | BD4: AT_Cost Center 3 | BE4: PVICMNT3 | BF4: INF3 | BG4: INF8 | BH4: INF13 | BI4: INF18 | BJ4: INF24 | BK4: 1.31 | BL4: 1.36 | BM4: 1.42 | BN4: 1.47 | BO4: 1.53 | BP4: 45852 | BQ4: 45853 | BR4: 45854 | BS4: 1 | BT4: 1 | BU4: 1
A5: AT_Product With SN 3 | B5: Products - Batches and Serial No | C5: AT_Product With SN 3 | D5: PSN3 | E5: 8967 | F5: G | G5: 1 | H5: 1 | I5: 1 | J5: AT_Product With SN 3,202541 | K5: 0 | L5: AT_Sales Return Acc 4 | M5: Nos | N5: Nos | O5: 1 | P5: AT_Branch 1_Location 1 Default Bin | Q5: 0 | R5: 1 | S5: 1 | T5: 1 | U5: 1 | V5: 4 | W5: 500.14 | X5: 500.14 | Y5: 250.14 | Z5: 250.14 | AA5: 1.11 | AB5: 2.78 | AC5: 1.17 | AD5: 2.93 | AE5: Per Quantity | AF5: 1.05 | AG5: 1.05 | AH5: Per Quantity | AI5: 1.21 | AJ5: 1.21 | AK5: % on Gross-Disc1&Disc2 | AL5: 1.26 | AM5: 3.12 | AN5: 0 | AO5: AT_HSN Code 1 | AP5: GST 12% | AQ5: CESS 1% | AR5: 239.05 | AS5: 12 | AT5: 14.34 | AU5: 14.34 | AV5: 0 | AW5: 2.39 | AX5: 31.07 | AY5: 270.12 | AZ5: 270.12 | BA5: AT_Department 4 | BB5: AT_Project 4 | BC5: AT_Profit Center 4 | BD5: AT_Cost Center 4 | BE5: PVICMNT4 | BF5: INF4 | BG5: INF9 | BH5: INF14 | BI5: INF19 | BJ5: INF25 | BK5: 1.32 | BL5: 1.37 | BM5: 1.43 | BN5: 1.48 | BO5: 1.54 | BP5: 45855 | BQ5: 45856 | BR5: 45857 | BS5: 1 | BT5: 1 | BU5: 1
A6: AT_Multi batch product 4 | B6: Products - MultiBatch | C6: AT_Multi batch product 4 | E6: 7777 | F6: G | G6: 1 | H6: 0 | I6: 1 | J6: AT_Multi batch product 4,202541 | K6: 0 | L6: AT_Sales Return Acc 5 | M6: Nos | N6: Nos | O6: 1 | P6: AT_Branch 1_Location 1 Default Bin | Q6: 0 | R6: 1.12 | S6: 1.12 | T6: 1.11 | U6: 1.11 | V6: 5 | W6: 500.15 | X6: 560.17 | Y6: 250.15 | Z6: 280.17 | AA6: 1.11 | AB6: 3.11 | AC6: 1.18 | AD6: 3.31 | AE6: Value | AF6: 1.06 | AG6: 1.06 | AH6: Value | AI6: 1.22 | AJ6: 1.22 | AK6: % on Gross-Disc2 | AL6: 1.27 | AM6: 3.54 | AN6: 0 | AO6: AT_HSN Code 2 | AP6: GST 18% | AQ6: CESS 10% | AR6: 267.93 | AS6: 18 | AT6: 24.11 | AU6: 24.11 | AV6: 0 | AW6: 26.79 | AX6: 75.01 | AY6: 342.94 | AZ6: 342.94 | BA6: AT_Department 5 | BB6: AT_Project 5 | BC6: AT_Profit Center 5 | BD6: AT_Cost Center 5 | BE6: PVICMNT5 | BF6: INF5 | BG6: INF10 | BH6: INF15 | BI6: INF20 | BJ6: INF26 | BK6: 1.33 | BL6: 1.38 | BM6: 1.44 | BN6: 1.49 | BO6: 1.55 | BP6: 45858 | BQ6: 45859 | BR6: 45860 | BS6: 1 | BT6: 1 | BU6: 1
Z8: =Y2*R2 -> 280.87353 | AB8: =$Z8*AA2% -> 3.1176962 | AD8: =$Z8*AC2% -> 3.1457835 | AG8: =$Z8*AF2% -> 2.86491 | AJ8: =$Z8*AI2% -> 3.0053468 | AM8: =$Z8*AL2% -> 3.4547444 | AR8: =$Z8-SUM(AA8:AM8) -> 265.28505 | AX8: =AR8*AS2% -> 31.834206 | AY8: =ROUND(AR8+AX8,2) -> 297.12
Z9: =Y3*R3 -> 281.13488 | AB9: =$Z9*AA3% -> 3.1205972 | AD9: =$Z9*AC3% -> 3.1768241 | AG9: =$Z9*AF3% -> 2.8956893 | AJ9: =($Z9-$AG9)*AI3% -> 3.0049833 | AM9: =($Z9-$AG9)*AL3% -> 3.450166 | AR9: =$Z9-SUM(AA9:AM9) -> 265.48662 | AX9: =AR9*AS3% -> 31.858394 | AY9: =ROUND(AR9+AX9,2) -> 297.35
Z10: =Y4*R4 -> 112.74638 | AB10: =$Z10*AA4% -> 1.2514848 | AD10: =$Z10*AC4% -> 1.307858 | AG10: =($Z10-$AB10-$AD10)*AF4% -> 1.1459452 | AJ10: =($Z10-$AB10-$AD10-$AG10)*AI4% -> 1.1885479 | AM10: =($Z10-$AB10-$AD10-$AG10)*AL4% -> 1.3630136 | AR10: =$Z10-SUM(AA10:AM10) -> 106.48953 | AX10: =AR10*AS4% -> 19.168115 | AY10: =ROUND(AR10+AX10,2) -> 125.66
Z11: =Y5*R5 -> 250.14 | AB11: =$Z11*AA5% -> 2.776554 | AD11: =$Z11*AC5% -> 2.926638 | AG11: =$R5*AF5 -> 1.05 | AJ11: =$R5*AI5 -> 1.21 | AM11: =($Z11-$AG11-$AJ11)*AL5% -> 3.123288 | AR11: =$Z11-SUM(AA11:AM11) -> 239.05352 | AX11: =AR11*AS5% -> 28.686422 | AY11: =ROUND(AR11+AX11,2) -> 267.74
Z12: =Y6*R6 -> 280.168 | AB12: =$Z12*AA6% -> 3.1098648 | AD12: =$Z12*AC6% -> 3.3059824 | AG12: =AF6 -> 1.06 | AJ12: =AI6 -> 1.22 | AM12: =($Z12-$AJ12)*AL6% -> 3.5426396 | AR12: =$Z12-SUM(AA12:AM12) -> 267.92951 | AX12: =AR12*AS6% -> 48.227312 | AY12: =ROUND(AR12+AX12,2) -> 316.16
Z14: =SUM(Z8:Z12) -> 1205.0628 | AB14: =SUM(AB8:AB12) -> 13.376197 | AD14: =SUM(AD8:AD12) -> 13.863086 | AG14: =SUM(AG8:AG12) -> 9.0165445 | AJ14: =SUM(AJ8:AJ12) -> 9.6288779 | AM14: =SUM(AM8:AM12) -> 14.933852 | AR14: =SUM(AR8:AR12) -> 1144.2442 | AX14: =SUM(AX8:AX12) -> 159.77445 | AY14: =SUM(AY8:AY12) -> 1304.03
R15: =SUM(R2:R6) -> 5.493 | T15: =SUM(T2:T6) -> 5.33 | Z15: =SUM(Z2:Z6) -> 1205.06 | AB15: =SUM(AB2:AB6) -> 13.38 | AD15: =SUM(AD2:AD6) -> 13.88 | AG15: =SUM(AG2:AG6) -> 9.04 | AJ15: =SUM(AJ2:AJ6) -> 9.66 | AM15: =SUM(AM2:AM6) -> 14.95 | AR15: =SUM(AR2:AR6) -> 1144.15 | AT15: =SUM(AT2:AT6) -> 79.88 | AU15: =SUM(AU2:AU6) -> 79.88 | AV15: =SUM(AV2:AV6) -> 0 | AW15: =SUM(AW2:AW6) -> 45.12 | AX15: =SUM(AX2:AX6) -> 204.88 | AY15: =SUM(AY2:AY6) -> 1349.03

Sheet ChargesAndDeductions
A1: ChargesOrDeductions | B1: AccountCode | C1: Account | D1: Basis | E1: BasisValue | F1: Percentage | G1: CalculateByQuantity | H1: Amount | I1: Charges | J1: ChargesInCompanyCurrency | K1: Deductions | L1: DeductionsInCompanyCurrency | M1: Department | N1: Project | O1: ProfitCentre | P1: CostCentre | Q1: Comments
A2: Charges | B2: AT_Charges Acc 1 | C2: AT_Charges Acc 1 | D2: Gross Minus Disc | E2: 1144.15 | F2: 1.6 | G2: 0 | H2: 18.31 | I2: 18.31 | J2: 18.31 | K2: 0 | L2: 0 | M2: Department 11 | N2: Projects 11 | O2: Profit Centre 11 | P2: Cost Centre 11 | Q2: PVCDCMNTS1
A3: Charges | B3: AT_Charges Acc 2 | C3: AT_Charges Acc 2 | D3: Gross Amt | E3: 1205.06 | F3: 1.56 | G3: 0 | H3: 18.8 | I3: 18.8 | J3: 18.8 | K3: 0 | L3: 0 | M3: Department 14 | N3: Projects 14 | O3: Profit Centre 14 | P3: Cost Centre 14 | Q3: PVCDCMNTS2
A4: Deductions | B4: AT_Deductions Acc 1 | C4: AT_Deductions Acc 1 | D4: Gross Minus Disc | E4: 1144.15 | F4: 1.57 | G4: 0 | H4: 17.96 | I4: 0 | J4: 0 | K4: 17.96 | L4: 17.96 | M4: Department 13 | N4: Projects 13 | O4: Profit Centre 13 | P4: Cost Centre 13 | Q4: PVCDCMNTS3
A5: Deductions | B5: AT_Deductions Acc 2 | C5: AT_Deductions Acc 2 | D5: Net Amt | E5: 1349.03 | F5: 1.58 | G5: 0 | H5: 21.31 | I5: 0 | J5: 0 | K5: 21.31 | L5: 21.31 | M5: Department 12 | N5: Projects 12 | O5: Profit Centre 12 | P5: Cost Centre 12 | Q5: PVCDCMNTS4
A6: Deductions | B6: AT_Deductions Acc 3 | C6: AT_Deductions Acc 3 | D6: NetAmount Plus Charges Minus Deductions | E6: 1346.87 | F6: 1.59 | G6: 0 | H6: 21.42 | I6: 0 | J6: 0 | K6: 21.42 | L6: 21.42 | M6: Department 15 | N6: Projects 15 | O6: Profit Centre 15 | P6: Cost Centre 15 | Q6: PVCDCMNTS5
E8: =SUM(E2:E6) -> 6189.26 | H8: =SUM(H2:H6) -> 97.8 | I8: =SUM(I2:I6) -> 37.11 | K8: =SUM(K2:K6) -> 60.69
E10: =Items!$AR$14 -> 1144.2442 | H10: =E10*F2% -> 18.307908 | I10: =H10 -> 18.307908
E11: =Items!$Z$14 -> 1205.0628 | H11: =E11*F3% -> 18.79898 | I11: =H11 -> 18.79898
E12: =Items!$AR$14 -> 1144.2442 | H12: =E12*F4% -> 17.964634 | K12: =H12 -> 17.964634
E13: =Items!$AY$14 -> 1304.03 | H13: =E13*F5% -> 20.603674 | K13: =H13 -> 20.603674
E14: =Items!$AY$14 -> 1304.03 | H14: =E14*F6% -> 20.734077 | K14: =H14 -> 20.734077
E16: =SUM(E10:E14) -> 6101.6113 | H16: =SUM(H10:H14) -> 96.409273 | I16: =SUM(I10:I14) -> 37.106887 | K16: =SUM(K10:K14) -> 59.302385

Sheet OtherCharges
A1: AccountCode | B1: Account | C1: HSNCode | D1: GoodsOrServices | E1: UOM | F1: Quantity | G1: InclusiveTax | H1: Amount | I1: AmountInCompanyCurrency | J1: HSN | K1: GSTProductCategory | L1: CESSProductCategory | M1: GSTAssessableValue | N1: GSTPercentage | O1: CGST | P1: SGST | Q1: IGST | R1: CESS | S1: GSTAmount | T1: NetAmount | U1: NetAmountInCompanyCurrency | V1: Department | W1: Project | X1: ProfitCentre | Y1: CostCentre | Z1: Comments
A2: AT_Charges Acc 3 | B2: AT_Charges Acc 3 | C2: 1111 | D2: S | E2: Nos | F2: 1 | G2: 0 | H2: 1.49 | I2: 1.49 | J2: AT_HSN Code 3 | K2: GST 1.5% | L2: CESS 1% | M2: 1.49 | N2: 1.5 | O2: 0.01 | P2: 0.01 | Q2: 0 | R2: 0.01 | S2: 0.03 | T2: 1.52 | U2: 1.52 | V2: Department 16 | W2: Projects 16 | X2: Profit Centre 16 | Y2: Cost Centre 16 | Z2: PVOCCMNTS1
A3: AT_Charges Acc 7 | B3: AT_Charges Acc 7 | C3: 7777 | D3: G | E3: Nos | F3: 1 | G3: 0 | H3: 1.45 | I3: 1.45 | J3: AT_HSN Code 2 | K3: GST 18% | L3: CESS 10% | M3: 1.45 | N3: 18 | O3: 0.13 | P3: 0.13 | Q3: 0 | R3: 0.15 | S3: 0.41 | T3: 1.86 | U3: 1.86 | V3: Department 17 | W3: Projects 17 | X3: Profit Centre 17 | Y3: Cost Centre 17 | Z3: PVOCCMNTS2
A4: AT_Charges Acc 4 | B4: AT_Charges Acc 4 | C4: 5689 | D4: G | E4: Nos | F4: 1 | G4: 0 | H4: 1.46 | I4: 1.46 | J4: AT_HSN Code 4 | K4: GST 12% | L4: CESS 1% | M4: 1.46 | N4: 12 | O4: 0.09 | P4: 0.09 | Q4: 0 | R4: 0.01 | S4: 0.19 | T4: 1.65 | U4: 1.65 | V4: Department 18 | W4: Projects 18 | X4: Profit Centre 18 | Y4: Cost Centre 18 | Z4: PVOCCMNTS3
A5: AT_Charges Acc 5 | B5: AT_Charges Acc 5 | C5: 3456 | D5: G | E5: Nos | F5: 1 | G5: 0 | H5: 1.47 | I5: 1.47 | J5: AT_HSN Code 5 | K5: GST 28% | L5: CESS 15% | M5: 1.47 | N5: 28 | O5: 0.21 | P5: 0.21 | Q5: 0 | R5: 0.22 | S5: 0.64 | T5: 2.11 | U5: 2.11 | V5: Department 19 | W5: Projects 19 | X5: Profit Centre 19 | Y5: Cost Centre 19 | Z5: PVOCCMNTS4
A6: AT_Charges Acc 6 | B6: AT_Charges Acc 6 | C6: 8764 | D6: G | E6: Nos | F6: 1 | G6: 0 | H6: 1.48 | I6: 1.48 | J6: AT_HSN Code 6 | K6: GST 3% | L6: CESS 1% | M6: 1.48 | N6: 3 | O6: 0.02 | P6: 0.02 | Q6: 0 | R6: 0.01 | S6: 0.05 | T6: 1.53 | U6: 1.53 | V6: Department 20 | W6: Projects 20 | X6: Profit Centre 20 | Y6: Cost Centre 20 | Z6: PVOCCMNTS5

Sheet SerialNos
A1: Product | B1: Batch | C1: Bin | D1: SerialNo | E1: Quantity | F1: FreeQuantity
A2: AT_Product With SN 3 | B2: AT_Product With SN 3,202541 | C2: AT_Branch 1_Location 1 Default Bin | D2: EFGH0 | E2: 1 | F2: 0
A3: AT_Product With SN 3 | B3: AT_Product With SN 3,202541 | C3: AT_Branch 1_Location 1 Default Bin | D3: ABCD0 | E3: 0 | F3: 1

Sheet CGST
A1: GSTSubType | B1: GSTSubTypeNature | C1: GSTProductCategory | D1: AssessableRate | E1: Basis | F1: AbatementPercentage | G1: AbsoluteTaxAmount | H1: AssessableValue | I1: Quantity | J1: TaxAmount | K1: TaxAmountInCompanyCurrency | L1: EditableTaxAmount | M1: TaxAccount | N1: InputCreditAvailable | O1: InputCredit | P1: InputCreditAmount | Q1: DeferredCredit | R1: DeferredCreditAmount | S1: ReverseChargeApplicable | T1: ExpenseAccount | U1: TaxAmountDue | V1: TaxAmountForCosting | W1: TaxPendingType
A2: CGST | B2: Base Tax | C2: GST 1.5% | D2: 0.75 | E2: Gross Amount Minus Discount | F2: 0 | G2: 0 | H2: 1.49 | I2: 0 | J2: 0.01 | K2: 0.01 | L2: 0 | M2: CGST Output Tax Account | N2: 0 | O2: 0 | P2: 0 | Q2: 0 | R2: 0 | S2: 0 | U2: 0 | V2: 0 | W2: 2101
A3: CGST | B3: Base Tax | C3: GST 18% | D3: 9 | E3: Gross Amount Minus Discount | F3: 0 | G3: 0 | H3: 1.45 | I3: 0 | J3: 0.13 | K3: 0.13 | L3: 0 | M3: CGST Output Tax Account | N3: 0 | O3: 0 | P3: 0 | Q3: 0 | R3: 0 | S3: 0 | U3: 0 | V3: 0 | W3: 2101
A4: CGST | B4: Base Tax | C4: GST 12% | D4: 6 | E4: Gross Amount Minus Discount | F4: 0 | G4: 0 | H4: 1.46 | I4: 0 | J4: 0.09 | K4: 0.09 | L4: 0 | M4: CGST Output Tax Account | N4: 0 | O4: 0 | P4: 0 | Q4: 0 | R4: 0 | S4: 0 | U4: 0 | V4: 0 | W4: 2101
A5: CGST | B5: Base Tax | C5: GST 28% | D5: 14 | E5: Gross Amount Minus Discount | F5: 0 | G5: 0 | H5: 1.47 | I5: 0 | J5: 0.21 | K5: 0.21 | L5: 0 | M5: CGST Output Tax Account | N5: 0 | O5: 0 | P5: 0 | Q5: 0 | R5: 0 | S5: 0 | U5: 0 | V5: 0 | W5: 2101
A6: CGST | B6: Base Tax | C6: GST 3% | D6: 1.5 | E6: Gross Amount Minus Discount | F6: 0 | G6: 0 | H6: 1.48 | I6: 0 | J6: 0.02 | K6: 0.02 | L6: 0 | M6: CGST Output Tax Account | N6: 0 | O6: 0 | P6: 0 | Q6: 0 | R6: 0 | S6: 0 | U6: 0 | V6: 0 | W6: 2101
A7: CGST | B7: Base Tax | C7: GST 12% | D7: 6 | E7: Gross Amount Minus Discount | F7: 0 | G7: 0 | H7: 265.28 | I7: 1.123 | J7: 15.92 | K7: 15.92 | L7: 0 | M7: CGST Output Tax Account | N7: 0 | O7: 0 | P7: 0 | Q7: 0 | R7: 0 | S7: 0 | U7: 0 | V7: 0 | W7: 2101
A8: CGST | B8: Base Tax | C8: GST 12% | D8: 6 | E8: Gross Amount Minus Discount | F8: 0 | G8: 0 | H8: 265.48 | I8: 1.124 | J8: 15.93 | K8: 15.93 | L8: 0 | M8: CGST Output Tax Account | N8: 0 | O8: 0 | P8: 0 | Q8: 0 | R8: 0 | S8: 0 | U8: 0 | V8: 0 | W8: 2101
A9: CGST | B9: Base Tax | C9: GST 18% | D9: 9 | E9: Gross Amount Minus Discount | F9: 0 | G9: 0 | H9: 106.41 | I9: 1.126 | J9: 9.58 | K9: 9.58 | L9: 0 | M9: CGST Output Tax Account | N9: 0 | O9: 0 | P9: 0 | Q9: 0 | R9: 0 | S9: 0 | U9: 0 | V9: 0 | W9: 2101
A10: CGST | B10: Base Tax | C10: GST 12% | D10: 6 | E10: Gross Amount Minus Discount | F10: 0 | G10: 0 | H10: 239.05 | I10: 1 | J10: 14.34 | K10: 14.34 | L10: 0 | M10: CGST Output Tax Account | N10: 0 | O10: 0 | P10: 0 | Q10: 0 | R10: 0 | S10: 0 | U10: 0 | V10: 0 | W10: 2101
A11: CGST | B11: Base Tax | C11: GST 18% | D11: 9 | E11: Gross Amount Minus Discount | F11: 0 | G11: 0 | H11: 267.93 | I11: 1.12 | J11: 24.11 | K11: 24.11 | L11: 0 | M11: CGST Output Tax Account | N11: 0 | O11: 0 | P11: 0 | Q11: 0 | R11: 0 | S11: 0 | U11: 0 | V11: 0 | W11: 2101

Sheet SGST
A1: GSTSubType | B1: GSTSubTypeNature | C1: GSTProductCategory | D1: AssessableRate | E1: Basis | F1: AbatementPercentage | G1: AbsoluteTaxAmount | H1: AssessableValue | I1: Quantity | J1: TaxAmount | K1: TaxAmountInCompanyCurrency | L1: EditableTaxAmount | M1: TaxAccount | N1: InputCreditAvailable | O1: InputCredit | P1: InputCreditAmount | Q1: DeferredCredit | R1: DeferredCreditAmount | S1: ReverseChargeApplicable | T1: ExpenseAccount | U1: TaxAmountDue | V1: TaxAmountForCosting | W1: TaxPendingType
A2: SGST | B2: Base Tax | C2: GST 1.5% | D2: 0.75 | E2: Gross Amount Minus Discount | F2: 0 | G2: 0 | H2: 1.49 | I2: 0 | J2: 0.01 | K2: 0.01 | L2: 0 | M2: SGST Output Tax Account | N2: 0 | O2: 0 | P2: 0 | Q2: 0 | R2: 0 | S2: 0 | U2: 0 | V2: 0 | W2: 2102
A3: SGST | B3: Base Tax | C3: GST 18% | D3: 9 | E3: Gross Amount Minus Discount | F3: 0 | G3: 0 | H3: 1.45 | I3: 0 | J3: 0.13 | K3: 0.13 | L3: 0 | M3: SGST Output Tax Account | N3: 0 | O3: 0 | P3: 0 | Q3: 0 | R3: 0 | S3: 0 | U3: 0 | V3: 0 | W3: 2102
A4: SGST | B4: Base Tax | C4: GST 12% | D4: 6 | E4: Gross Amount Minus Discount | F4: 0 | G4: 0 | H4: 1.46 | I4: 0 | J4: 0.09 | K4: 0.09 | L4: 0 | M4: SGST Output Tax Account | N4: 0 | O4: 0 | P4: 0 | Q4: 0 | R4: 0 | S4: 0 | U4: 0 | V4: 0 | W4: 2102
A5: SGST | B5: Base Tax | C5: GST 28% | D5: 14 | E5: Gross Amount Minus Discount | F5: 0 | G5: 0 | H5: 1.47 | I5: 0 | J5: 0.21 | K5: 0.21 | L5: 0 | M5: SGST Output Tax Account | N5: 0 | O5: 0 | P5: 0 | Q5: 0 | R5: 0 | S5: 0 | U5: 0 | V5: 0 | W5: 2102
A6: SGST | B6: Base Tax | C6: GST 3% | D6: 1.5 | E6: Gross Amount Minus Discount | F6: 0 | G6: 0 | H6: 1.48 | I6: 0 | J6: 0.02 | K6: 0.02 | L6: 0 | M6: SGST Output Tax Account | N6: 0 | O6: 0 | P6: 0 | Q6: 0 | R6: 0 | S6: 0 | U6: 0 | V6: 0 | W6: 2102
A7: SGST | B7: Base Tax | C7: GST 12% | D7: 6 | E7: Gross Amount Minus Discount | F7: 0 | G7: 0 | H7: 265.28 | I7: 1.123 | J7: 15.92 | K7: 15.92 | L7: 0 | M7: SGST Output Tax Account | N7: 0 | O7: 0 | P7: 0 | Q7: 0 | R7: 0 | S7: 0 | U7: 0 | V7: 0 | W7: 2102
A8: SGST | B8: Base Tax | C8: GST 12% | D8: 6 | E8: Gross Amount Minus Discount | F8: 0 | G8: 0 | H8: 265.48 | I8: 1.124 | J8: 15.93 | K8: 15.93 | L8: 0 | M8: SGST Output Tax Account | N8: 0 | O8: 0 | P8: 0 | Q8: 0 | R8: 0 | S8: 0 | U8: 0 | V8: 0 | W8: 2102
A9: SGST | B9: Base Tax | C9: GST 18% | D9: 9 | E9: Gross Amount Minus Discount | F9: 0 | G9: 0 | H9: 106.41 | I9: 1.126 | J9: 9.58 | K9: 9.58 | L9: 0 | M9: SGST Output Tax Account | N9: 0 | O9: 0 | P9: 0 | Q9: 0 | R9: 0 | S9: 0 | U9: 0 | V9: 0 | W9: 2102
A10: SGST | B10: Base Tax | C10: GST 12% | D10: 6 | E10: Gross Amount Minus Discount | F10: 0 | G10: 0 | H10: 239.05 | I10: 1 | J10: 14.34 | K10: 14.34 | L10: 0 | M10: SGST Output Tax Account | N10: 0 | O10: 0 | P10: 0 | Q10: 0 | R10: 0 | S10: 0 | U10: 0 | V10: 0 | W10: 2102
A11: SGST | B11: Base Tax | C11: GST 18% | D11: 9 | E11: Gross Amount Minus Discount | F11: 0 | G11: 0 | H11: 267.93 | I11: 1.12 | J11: 24.11 | K11: 24.11 | L11: 0 | M11: SGST Output Tax Account | N11: 0 | O11: 0 | P11: 0 | Q11: 0 | R11: 0 | S11: 0 | U11: 0 | V11: 0 | W11: 2102

Sheet IGST
A1: GSTSubType | B1: GSTSubTypeNature | C1: GSTProductCategory | D1: AssessableRate | E1: Basis | F1: AbatementPercentage | G1: AbsoluteTaxAmount | H1: AssessableValue | I1: Quantity | J1: TaxAmount | K1: TaxAmountInCompanyCurrency | L1: EditableTaxAmount | M1: TaxAccount | N1: InputCreditAvailable | O1: InputCredit | P1: InputCreditAmount | Q1: DeferredCredit | R1: DeferredCreditAmount | S1: ReverseChargeApplicable | T1: ExpenseAccount | U1: TaxAmountDue | V1: TaxAmountForCosting | W1: TaxPendingType

Sheet CESS
A1: GSTSubType | B1: GSTSubTypeNature | C1: GSTProductCategory | D1: AssessableRate | E1: Basis | F1: AbatementPercentage | G1: AbsoluteTaxAmount | H1: AssessableValue | I1: Quantity | J1: TaxAmount | K1: TaxAmountInCompanyCurrency | L1: EditableTaxAmount | M1: TaxAccount | N1: InputCreditAvailable | O1: InputCredit | P1: InputCreditAmount | Q1: DeferredCredit | R1: DeferredCreditAmount | S1: ReverseChargeApplicable | T1: ExpenseAccount | U1: TaxAmountDue | V1: TaxAmountForCosting | W1: TaxPendingType
A2: CESS | B2: Base Tax | C2: CESS 1% | D2: 1 | E2: Gross Amount Minus Discount | F2: 0 | G2: 0 | H2: 1.49 | I2: 0 | J2: 0.01 | K2: 0.01 | L2: 0 | M2: GST Cess Output Tax Account | N2: 0 | O2: 0 | P2: 0 | Q2: 0 | R2: 0 | S2: 0 | U2: 0 | V2: 0 | W2: 2101
A3: CESS | B3: Base Tax | C3: CESS 10% | D3: 10 | E3: Gross Amount Minus Discount | F3: 0 | G3: 0 | H3: 1.45 | I3: 0 | J3: 0.15 | K3: 0.15 | L3: 0 | M3: GST Cess Output Tax Account | N3: 0 | O3: 0 | P3: 0 | Q3: 0 | R3: 0 | S3: 0 | U3: 0 | V3: 0 | W3: 2101
A4: CESS | B4: Base Tax | C4: CESS 1% | D4: 1 | E4: Gross Amount Minus Discount | F4: 0 | G4: 0 | H4: 1.46 | I4: 0 | J4: 0.01 | K4: 0.01 | L4: 0 | M4: GST Cess Output Tax Account | N4: 0 | O4: 0 | P4: 0 | Q4: 0 | R4: 0 | S4: 0 | U4: 0 | V4: 0 | W4: 2101
A5: CESS | B5: Base Tax | C5: CESS 15% | D5: 15 | E5: Gross Amount Minus Discount | F5: 0 | G5: 0 | H5: 1.47 | I5: 0 | J5: 0.22 | K5: 0.22 | L5: 0 | M5: GST Cess Output Tax Account | N5: 0 | O5: 0 | P5: 0 | Q5: 0 | R5: 0 | S5: 0 | U5: 0 | V5: 0 | W5: 2101
A6: CESS | B6: Base Tax | C6: CESS 1% | D6: 1 | E6: Gross Amount Minus Discount | F6: 0 | G6: 0 | H6: 1.48 | I6: 0 | J6: 0.01 | K6: 0.01 | L6: 0 | M6: GST Cess Output Tax Account | N6: 0 | O6: 0 | P6: 0 | Q6: 0 | R6: 0 | S6: 0 | U6: 0 | V6: 0 | W6: 2101
A7: CESS | B7: Base Tax | C7: CESS 1% | D7: 1 | E7: Gross Amount Minus Discount | F7: 0 | G7: 0 | H7: 265.28 | I7: 1.123 | J7: 2.65 | K7: 2.65 | L7: 0 | M7: GST Cess Output Tax Account | N7: 0 | O7: 0 | P7: 0 | Q7: 0 | R7: 0 | S7: 0 | U7: 0 | V7: 0 | W7: 2101
A8: CESS | B8: Base Tax | C8: CESS 1% | D8: 1 | E8: Gross Amount Minus Discount | F8: 0 | G8: 0 | H8: 265.48 | I8: 1.124 | J8: 2.65 | K8: 2.65 | L8: 0 | M8: GST Cess Output Tax Account | N8: 0 | O8: 0 | P8: 0 | Q8: 0 | R8: 0 | S8: 0 | U8: 0 | V8: 0 | W8: 2101
A9: CESS | B9: Base Tax | C9: CESS 10% | D9: 10 | E9: Gross Amount Minus Discount | F9: 0 | G9: 0 | H9: 106.41 | I9: 1.126 | J9: 10.64 | K9: 10.64 | L9: 0 | M9: GST Cess Output Tax Account | N9: 0 | O9: 0 | P9: 0 | Q9: 0 | R9: 0 | S9: 0 | U9: 0 | V9: 0 | W9: 2101
A10: CESS | B10: Base Tax | C10: CESS 1% | D10: 1 | E10: Gross Amount Minus Discount | F10: 0 | G10: 0 | H10: 239.05 | I10: 1 | J10: 2.39 | K10: 2.39 | L10: 0 | M10: GST Cess Output Tax Account | N10: 0 | O10: 0 | P10: 0 | Q10: 0 | R10: 0 | S10: 0 | U10: 0 | V10: 0 | W10: 2101
A11: CESS | B11: Base Tax | C11: CESS 10% | D11: 10 | E11: Gross Amount Minus Discount | F11: 0 | G11: 0 | H11: 267.93 | I11: 1.12 | J11: 26.79 | K11: 26.79 | L11: 0 | M11: GST Cess Output Tax Account | N11: 0 | O11: 0 | P11: 0 | Q11: 0 | R11: 0 | S11: 0 | U11: 0 | V11: 0 | W11: 2101

Sheet TCS
A1: TransactionNature | B1: AssessableValue | C1: TCSRate | D1: TCSAmount | E1: TCSAmountInCompanyCurrency | F1: TCSAccount
A2: AT_TCS Transaction Nature 1 | B2: 1357.7 | C2: 5 | D2: 67.88 | E2: 67.88 | F2: AT_TCS Collected Acc 1

Sheet BillsReceivable
A1: VoucherIdentityNo | B1: TowardsVNoDate | C1: VoucherIdentityNo1 | D1: ReferenceBillDetails | E1: Division | F1: DueDate | G1: PendingAmount | H1: Adjust | I1: AmountAdjusted | J1: BalanceDue

Sheet Cash
A1: CashAccountCode | B1: CashAccount | C1: Amount | D1: AmountInCompanyCurrency | E1: Department | F1: Project | G1: ProfitCentre | H1: CostCentre | I1: Comments
A2: AT_Cash Acc 1 | B2: AT_Cash Acc 1 | C2: 11.11 | D2: 11.11 | E2: Department 31 | F2: Projects 31 | G2: Profit Centre 31 | H2: Cost Centre 31 | I2: PVCCMNTS1
A3: AT_Cash Acc 2 | B3: AT_Cash Acc 2 | C3: 11.12 | D3: 11.12 | E3: Department 32 | F3: Projects 32 | G3: Profit Centre 32 | H3: Cost Centre 32 | I3: PVCCMNTS2
A4: AT_Cash Acc 3 | B4: AT_Cash Acc 3 | C4: 11.13 | D4: 11.13 | E4: Department 33 | F4: Projects 33 | G4: Profit Centre 33 | H4: Cost Centre 33 | I4: PVCCMNTS3
A5: AT_Cash Acc 4 | B5: AT_Cash Acc 4 | C5: 11.14 | D5: 11.14 | E5: Department 34 | F5: Projects 34 | G5: Profit Centre 34 | H5: Cost Centre 34 | I5: PVCCMNTS4
A6: AT_Cash Acc 5 | B6: AT_Cash Acc 5 | C6: 11.15 | D6: 11.15 | E6: Department 35 | F6: Projects 35 | G6: Profit Centre 35 | H6: Cost Centre 35 | I6: PVCCMNTS5

Sheet Cheques
A1: BankAccountCode | B1: BankAccount | C1: Amount | D1: AmountInCompanyCurrency | E1: ChequeNo | F1: ChequeDate | G1: ChargesAccountCode | H1: ChargesAccount | I1: Charges | J1: ChargesInCompanyCurrency | K1: NetAmount | L1: NetAmountInCompanyCurrency | M1: Department | N1: Project | O1: ProfitCentre | P1: CostCentre | Q1: Comments
A2: AT_Bank Acc 1 | B2: AT_Bank Acc 1 | C2: 12.11 | D2: 12.11 | E2: 1211 | F2: 45880 | G2: AT_Charges Acc 10 | H2: AT_Charges Acc 10 | I2: 1.21 | J2: 1.21 | K2: 13.32 | L2: 13.32 | M2: Department 36 | N2: Projects 36 | O2: Profit Centre 36 | P2: Cost Centre 36 | Q2: PVCHCMNTS1
A3: AT_Bank Acc 2 | B3: AT_Bank Acc 2 | C3: 12.12 | D3: 12.12 | E3: 1212 | F3: 45881 | G3: AT_Charges Acc 11 | H3: AT_Charges Acc 11 | I3: 1.22 | J3: 1.22 | K3: 13.34 | L3: 13.34 | M3: Department 37 | N3: Projects 37 | O3: Profit Centre 37 | P3: Cost Centre 37 | Q3: PVCHCMNTS2
A4: AT_Bank Acc 3 | B4: AT_Bank Acc 3 | C4: 12.13 | D4: 12.13 | E4: 1213 | F4: 45882 | G4: AT_Charges Acc 12 | H4: AT_Charges Acc 12 | I4: 1.23 | J4: 1.23 | K4: 13.36 | L4: 13.36 | M4: Department 38 | N4: Projects 38 | O4: Profit Centre 38 | P4: Cost Centre 38 | Q4: PVCHCMNTS3
A5: AT_Bank Acc 4 | B5: AT_Bank Acc 4 | C5: 12.14 | D5: 12.14 | E5: 1214 | F5: 45883 | G5: AT_Charges Acc 13 | H5: AT_Charges Acc 13 | I5: 1.24 | J5: 1.24 | K5: 13.38 | L5: 13.38 | M5: Department 39 | N5: Projects 39 | O5: Profit Centre 39 | P5: Cost Centre 39 | Q5: PVCHCMNTS4
A6: AT_Bank Acc 5 | B6: AT_Bank Acc 5 | C6: 12.15 | D6: 12.15 | E6: 1215 | F6: 45884 | G6: AT_Charges Acc 14 | H6: AT_Charges Acc 14 | I6: 1.25 | J6: 1.25 | K6: 13.4 | L6: 13.4 | M6: Department 40 | N6: Projects 40 | O6: Profit Centre 40 | P6: Cost Centre 40 | Q6: PVCHCMNTS5

Sheet PostDatedCheques
A1: BankAccountCode | B1: BankAccount | C1: PDCAccount | D1: Amount | E1: AmountInCompanyCurrency | F1: ChequeNo | G1: ChequeDate | H1: Department | I1: Project | J1: ProfitCentre | K1: CostCentre | L1: Comments
A2: AT_Bank_PDC_Acc 1 | B2: AT_Bank_PDC_Acc 1 | C2: PDC Account | D2: 13.11 | E2: 13.11 | F2: 1311 | G2: 45885 | H2: Department 41 | I2: Projects 41 | J2: Profit Centre 41 | K2: Cost Centre 41 | L2: PVPDCCMNT1
A3: AT_Bank_PDC_Acc 2 | B3: AT_Bank_PDC_Acc 2 | C3: PDC Account | D3: 13.12 | E3: 13.12 | F3: 1312 | G3: 45886 | H3: Department 42 | I3: Projects 42 | J3: Profit Centre 42 | K3: Cost Centre 42 | L3: PVPDCCMNT2
A4: AT_Bank_PDC_Acc 3 | B4: AT_Bank_PDC_Acc 3 | C4: PDC Account | D4: 13.13 | E4: 13.13 | F4: 1313 | G4: 45887 | H4: Department 43 | I4: Projects 43 | J4: Profit Centre 43 | K4: Cost Centre 43 | L4: PVPDCCMNT3
A5: AT_Bank_PDC_Acc 4 | B5: AT_Bank_PDC_Acc 4 | C5: PDC Account | D5: 13.14 | E5: 13.14 | F5: 1314 | G5: 45888 | H5: Department 44 | I5: Projects 44 | J5: Profit Centre 44 | K5: Cost Centre 44 | L5: PVPDCCMNT4
A6: AT_Bank_PDC_Acc 5 | B6: AT_Bank_PDC_Acc 5 | C6: PDC Account | D6: 13.15 | E6: 13.15 | F6: 1315 | G6: 45889 | H6: Department 45 | I6: Projects 45 | J6: Profit Centre 45 | K6: Cost Centre 45 | L6: PVPDCCMNT5

Sheet PDC
A1: BankAccountCode | B1: BankAccount | C1: Amount | D1: AmountInCompanyCurrency | E1: ChequeNo | F1: ChequeDate | G1: Department | H1: Project | I1: ProfitCentre | J1: CostCentre | K1: Comments
A2: BPDC5 | B2: AT_Bank_PDC_Acc 5 | C2: 14.11 | D2: 14.11 | E2: 1411 | F2: 45890 | G2: Department 46 | H2: Projects 46 | I2: Profit Centre 46 | J2: Cost Centre 46 | K2: BCPDCCMNTS1
A3: BPDC6 | B3: AT_Bank_PDC_Acc 6 | C3: 14.12 | D3: 14.12 | E3: 1412 | F3: 45891 | G3: Department 47 | H3: Projects 47 | I3: Profit Centre 47 | J3: Cost Centre 47 | K3: BCPDCCMNTS2
A4: BPDC7 | B4: AT_Bank_PDC_Acc 7 | C4: 14.13 | D4: 14.13 | E4: 1413 | F4: 45892 | G4: Department 48 | H4: Projects 48 | I4: Profit Centre 48 | J4: Cost Centre 48 | K4: BCPDCCMNTS3
A5: BPDC8 | B5: AT_Bank_PDC_Acc 8 | C5: 14.14 | D5: 14.14 | E5: 1414 | F5: 45893 | G5: Department 49 | H5: Projects 49 | I5: Profit Centre 49 | J5: Cost Centre 49 | K5: BCPDCCMNTS4
A6: BPDC9 | B6: AT_Bank_PDC_Acc 9 | C6: 14.15 | D6: 14.15 | E6: 1415 | F6: 45894 | G6: Department 50 | H6: Projects 50 | I6: Profit Centre 50 | J6: Cost Centre 50 | K6: BCPDCCMNTS5

Sheet EInvoiceDetails
A1: GSTEInvoiceRequired | B1: GenerateNow
A2: 1 | B2: 0

Sheet InvoiceDetails
A1: InvoiceValue | B1: InvoiceDate
A2: 1402 | B2: 45849

Sheet OtherInfo
A1: ReferenceBillNo | B1: ReferenceBillDate | C1: OtherInfo1 | D1: OtherInfo2 | E1: OtherInfo3 | F1: OtherInfo4 | G1: OtherInfo5
A2: PVRBN11 | B2: 45895 | C2: PVOI1 | D2: PVOI3 | E2: PVOI4 | F2: PVOI5 | G2: PVOI2

Sheet AdditionalInformation
A1: Info1 | B1: Info2 | C1: Info3 | D1: Info4 | E1: Info5 | F1: Value1 | G1: Value2 | H1: Value3 | I1: Value4 | J1: Value5 | K1: Date1 | L1: Date2 | M1: Date3 | N1: Bool1 | O1: Bool2 | P1: Bool3
A2: PVAI1 | B2: PVAI2 | C2: PVAI3 | D2: PVAI4 | E2: PVAI5 | F2: 15.11 | G2: 15.12 | H2: 15.13 | I2: 15.14 | J2: 15.15 | K2: 45896 | L2: 45897 | M2: 45898 | N2: 1 | O2: 1 | P2: 1

Sheet Summary
A1: Quantity | B1: QuantityInSKU | C1: FreeQuantity | D1: FreeQuantityInSKU | E1: GrossAmount | F1: Discount | G1: GrossMinusDiscount | H1: CGST | I1: SGST | J1: IGST | K1: CESS | L1: ItemsGSTAmount | M1: NetAmount | N1: Charges | O1: NetAmountAfterCharges | P1: Deductions | Q1: NetAmountAfterDeductions | R1: OtherCharges | S1: NetAmountAfterOtherCharges | T1: OtherChargesCGST | U1: OtherChargesSGST | V1: OtherChargesIGST | W1: OtherChargesCESS | X1: OtherChargesGST | Y1: TaxAmount | Z1: NetAmountAfterOtherChargesTaxAmount | AA1: Division | AB1: TCSTaxableValue | AC1: TCSTaxableValue1 | AD1: TCSTaxablevalue2 | AE1: EditTCSTaxablevalue | AF1: TCSAmount | AG1: NetAmountAfterTCS | AH1: RoundOffType | AI1: RoundOffAccount | AJ1: RoundOffAmount | AK1: RoundOffDebit | AL1: RoundOffDebitInCompanyCurrency | AM1: RoundOffCredit | AN1: RoundOffCreditInCompanyCurrency | AO1: TotalValue | AP1: TotalValueInCompanyCurrency | AQ1: BillsReceivableAdjusted | AR1: NetAmountAfterBillsAdjusted | AS1: Cash | AT1: Cheques | AU1: PostDatedCheques | AV1: PDC | AW1: TotalPostDatedCheques | AX1: PaymentsValue | AY1: NetAmountAfterPayment | AZ1: PayableAmount | BA1: ReceivableAmount | BB1: TotalChargesByValue | BC1: TotalChargesByQty | BD1: TotalDeductionsByValue | BE1: TotalDeductionsByQty | BF1: TaxAdjustment1 | BG1: TaxAdjustment2 | BH1: TaxAdjustment | BI1: GSTAssessableValue1 | BJ1: GSTAssessableValue2 | BK1: GSTAssessableValue
A2: 5.493 | B2: 5.493 | C2: 5.33 | D2: 5.33 | E2: 1205.06 | F2: 60.91 | G2: 1144.15 | H2: 79.88 | I2: 79.88 | J2: 0 | K2: 45.12 | L2: 204.88 | M2: 1349.03 | N2: 37.11 | O2: 1386.14 | P2: 60.69 | Q2: 1325.45 | R2: 7.35 | S2: 1332.8 | T2: 0.46 | U2: 0.46 | V2: 0 | W2: 0.4 | X2: 1.32 | Y2: 206.2 | Z2: 1334.12 | AA2: 24D Books Fin AT | AB2: 1357.7 | AC2: 1349.03 | AD2: 8.67 | AE2: 0 | AF2: 67.88 | AG2: 1402 | AH2: 1 | AJ2: 0 | AK2: 0 | AL2: 0 | AM2: 0 | AN2: 0 | AO2: 1402 | AP2: 1402 | AQ2: 0 | AR2: 1402 | AS2: 55.65 | AT2: 60.65 | AU2: 65.65 | AV2: 70.65 | AW2: 136.3 | AX2: 252.6 | AY2: 1149.4 | AZ2: 1149.4 | BA2: 0 | BB2: 37.11 | BC2: 0 | BD2: 60.69 | BE2: 0 | BF2: 0 | BG2: 0 | BH2: 0 | BI2: 1144.15 | BJ2: 7.35 | BK2: 1151.5

Sheet BillingAddress
A1: PartyAccount | B1: GSTIN | C1: Address1 | D1: Address2 | E1: Address3 | F1: City | G1: State | H1: StateCode | I1: Country | J1: Zip | K1: TelephoneNo | L1: MobileNo
A2: At_Cus_Reg_Intra | B2: 36AAFCB7707D1ZV | C2: ,Plot No 11, 4th Floor | D2: Hyderabad | E2: Yashshree Tech Park, HITEC City, Hyderabad, Telangana | F2: Hyderabad | G2: Telangana | H2: 36 | I2: India | J2: 500081

Sheet ShippingAddress
A1: PartyAccount | B1: GSTIN | C1: Address1 | D1: Address2 | E1: Address3 | F1: City | G1: State | H1: StateCode | I1: Country | J1: Zip | K1: TelephoneNo | L1: MobileNo
A2: At_Cus_Reg_Intra | B2: 36AAFCB7707D1ZV | C2: ,Plot No 11, 4th Floor | D2: Hyderabad | E2: Yashshree Tech Park, HITEC City, Hyderabad, Telangana | F2: Hyderabad | G2: Telangana | H2: 36 | I2: India | J2: 500081 | K2: 040-2894-5896 | L2: 9755884123

Sheet TermsAndConditions
A1: TermType | B1: Term | C1: Comments
A2: AT_Term Type 1 | B2: AT_Term 1 | C2: PVTCMNTS1
A3: AT_Term Type 2 | B3: AT_Term 2 | C3: PVTCMNTS2
A4: AT_Term Type 3 | B4: AT_Term 3 | C4: PVTCMNTS3
A5: AT_Term Type 4 | B5: AT_Term 4 | C5: PVTCMNTS4
A6: AT_Term Type 5 | B6: AT_Term 5 | C6: PVTCMNTS5

Sheet Allocations
A1: Department | B1: Project | C1: ProfitCentre | D1: CostCentre
A2: Department 1 | B2: Project 1 | C2: Profit Centre 1 | D2: Cost Centre 1
